servicenow_mcp/__init__.py
servicenow_mcp/cli.py
servicenow_mcp/server.py
servicenow_mcp/server_sse.py
servicenow_mcp/auth/__init__.py
servicenow_mcp/auth/auth_manager.py
servicenow_mcp/tools/__init__.py
servicenow_mcp/tools/catalog_optimization.py
servicenow_mcp/tools/catalog_tools.py
servicenow_mcp/tools/catalog_variables.py
servicenow_mcp/tools/change_tools.py
servicenow_mcp/tools/changeset_tools.py
servicenow_mcp/tools/epic_tools.py
servicenow_mcp/tools/incident_tools.py
servicenow_mcp/tools/knowledge_base.py
servicenow_mcp/tools/project_tools.py
servicenow_mcp/tools/script_include_tools.py
servicenow_mcp/tools/scrum_task_tools.py
servicenow_mcp/tools/story_tools.py
servicenow_mcp/tools/user_tools.py
servicenow_mcp/tools/workflow_tools.py
servicenow_mcp/utils/__init__.py
servicenow_mcp/utils/config.py
servicenow_mcp/utils/tool_utils.py
mseep_servicenow_mcp-0.1.6.dist-info/METADATA
mseep_servicenow_mcp-0.1.6.dist-info/WHEEL
mseep_servicenow_mcp-0.1.6.dist-info/entry_points.txt
mseep_servicenow_mcp-0.1.6.dist-info/licenses/LICENSE
mseep_servicenow_mcp-0.1.6.dist-info/RECORD
